philosophos/__init__.py
philosophos-0.0.1.dist-info/LICENSE
philosophos-0.0.1.dist-info/METADATA
philosophos-0.0.1.dist-info/WHEEL
philosophos-0.0.1.dist-info/top_level.txt
philosophos-0.0.1.dist-info/RECORD
