Metadata-Version: 2.1
Name: philosophos
Version: 0.0.1
Summary: φῐλόσοφος • (philósophos) philosopher
Author-email: Alexander Fedotov <alex.fedotov@aol.com>
Project-URL: Homepage, https://github.com/alxfed/philosophos
Project-URL: Bug Tracker, https://github.com/alxfed/philosophos/issues
Classifier: Programming Language :: Python :: 3
Classifier: License :: OSI Approved :: MIT License
Classifier: Operating System :: OS Independent
Requires-Python: >=3.10
License-File: LICENSE
